LICENSE
MANIFEST.in
README.rst
pyproject.toml
setup.cfg
setup.py
django_webperformers_humans.egg-info/PKG-INFO
django_webperformers_humans.egg-info/SOURCES.txt
django_webperformers_humans.egg-info/dependency_links.txt
django_webperformers_humans.egg-info/requires.txt
django_webperformers_humans.egg-info/top_level.txt
humans/__init__.py
humans/admin.py
humans/apps.py
humans/models.py
humans/sitemap.py
humans/tests.py
humans/urls.py
humans/views.py
humans/helpers/__init__.py
humans/helpers/generic.py
humans/helpers/images.py
humans/helpers/team.py
humans/migrations/0001_initial.py
humans/migrations/0002_human_metadescription.py
humans/migrations/0003_alter_human_metadescription.py
humans/migrations/0004_human_metatitle.py
humans/migrations/__init__.py
humans/signals/__init__.py
humans/signals/humans.py
humans/templates/humans/personPage.html
humans/templates/humans/teamComponent.html
humans/templates/humans/teamPage.html
humans/templatetags/__init__.py
humans/templatetags/images.py